kams/__init__.py
kams/__main__.py
kams/utils/datatypes.py
kams-0.1.4.dist-info/entry_points.txt
kams-0.1.4.dist-info/LICENSE
kams-0.1.4.dist-info/WHEEL
kams-0.1.4.dist-info/METADATA
kams-0.1.4.dist-info/RECORD
