Metadata-Version: 2.1
Name: kams
Version: 0.1.4
Summary: A macro lang for KeeperRL
License: MIT
Author: GameDungeon
Author-email: gamedungeon@protonmail.com
Requires-Python: >=3.9,<4.0
Classifier: License :: OSI Approved :: MIT License
Classifier: Programming Language :: Python :: 3
Classifier: Programming Language :: Python :: 3.9
Requires-Dist: click (>=8.0.3,<9.0.0)
Requires-Dist: click-default-group (>=1.2.2,<2.0.0)
